src/ba_pipelined.v
 module pipelined_mult (
    input clk,
    input rst,
    input [31:0] a,
    input [31:0] b,
    output reg [63:0] p
);

    // --- STAGE 1: INPUT SPLIT ---
    reg [15:0] a_h, a_l;
    reg [15:0] b_h, b_l;

    always @(posedge clk) begin
        if (rst) begin
            a_h <= 0; a_l <= 0; b_h <= 0; b_l <= 0;
        end else begin
            a_h <= a[31:16]; a_l <= a[15:0];
            b_h <= b[31:16]; b_l <= b[15:0];
        end
    end

    // --- STAGE 2: MULTIPLICATION ---
    reg [31:0] p_hh, p_hl, p_lh, p_ll;

    always @(posedge clk) begin
        if (rst) begin
            p_hh <= 0; p_hl <= 0; p_lh <= 0; p_ll <= 0;
        end else begin
            p_hh <= a_h * b_h;
            p_hl <= a_h * b_l;
            p_lh <= a_l * b_h;
            p_ll <= a_l * b_l;
        end
    end

    // --- STAGE 3: FIRST ADDITION (Cộng các phần chéo trước) ---
    // Thay vì cộng tất cả, nhịp này chỉ cộng HL + LH thôi cho nhẹ.
    reg [32:0] mid_sum;
    reg [31:0] p_hh_pipe, p_ll_pipe;

    always @(posedge clk) begin
        if (rst) begin
            mid_sum <= 0; p_hh_pipe <= 0; p_ll_pipe <= 0;
        end else begin
            mid_sum <= p_hl + p_lh; // Chỉ làm mỗi việc cộng 2 số này
            p_hh_pipe <= p_hh;      // Mấy cái kia chỉ việc đi chơi (truyền thẳng)
            p_ll_pipe <= p_ll;
        end
    end

    // --- STAGE 4: SECOND ADDITION (Chuẩn bị số hạng) ---
    // Tách việc dịch bit và cộng ra
    reg [63:0] term_high, term_mid, term_low;

    always @(posedge clk) begin
         if (rst) begin
            term_high <= 0; term_mid <= 0; term_low <= 0;
         end else begin
            term_high <= {32'b0, p_hh_pipe} << 32;
            term_mid  <= {31'b0, mid_sum}   << 16;
            term_low  <= {32'b0, p_ll_pipe};
         end
    end

    // --- STAGE 5: FINAL MERGE ---
    // Cộng 3 số hạng cuối cùng
    always @(posedge clk) begin
        if (rst) p <= 0;
        else p <= term_high + term_mid + term_low;
    end

endmodule

verify/pipelined_mult_tb.v
`timescale 1ns / 1ps

module tb_pipelined_mult;

    // 1. Tín hiệu giao tiếp với DUT
    reg clk;
    reg rst;
    reg [31:0] a;
    reg [31:0] b;
    wire [63:0] p;

    // 2. Gọi Module (Device Under Test)
    pipelined_mult uut (
        .clk(clk),
        .rst(rst),
        .a(a),
        .b(b),
        .p(p)
    );

    // 3. Tạo Clock 500MHz (Chu kỳ 2ns)
    initial begin
        clk = 0;
        forever #1 clk = ~clk; 
    end

    // 4. PIPELINE REFERENCE MODEL (Mô hình tham chiếu)
    // Vì mạch DUT có 5 tầng thanh ghi, ta cần 5 biến trễ để so sánh
    reg [63:0] exp_1, exp_2, exp_3, exp_4, exp_5;
    reg [63:0] exp_final; // Biến này sẽ nối với exp_5

    // Logic tính toán kết quả đúng (Behavioral) - Chạy ở cạnh LÊN
    always @(posedge clk) begin
        if (rst) begin
            exp_1 <= 0; exp_2 <= 0; exp_3 <= 0; 
            exp_4 <= 0; exp_5 <= 0;
        end else begin
            // Bước 1: Tính toán chuẩn (Golden calculation)
            // Ép kiểu về 64-bit trước khi nhân để tránh tràn số
            exp_1 <= {32'd0, a} * {32'd0, b}; 
            
            // Bước 2: Dịch chuyển qua 5 giai đoạn để khớp với độ trễ của DUT
            exp_2 <= exp_1;
            exp_3 <= exp_2;
            exp_4 <= exp_3;
            exp_5 <= exp_4; 
            // Sau dòng này, exp_5 chứa kết quả ứng với input của 5 chu kỳ trước
        end
    end

    // Gán kết quả mong đợi cuối cùng
    always @(*) exp_final = exp_5;

    // 5. CHECKER (Trọng tài) - Chạy ở cạnh XUỐNG
    // Kiểm tra lệch pha để đảm bảo tín hiệu đã ổn định
    integer error_count = 0;
    
    always @(negedge clk) begin
        if (!rst && $time > 20) begin // Bỏ qua giai đoạn Reset
            if (p !== exp_final) begin
                $display("[ERROR] Time %0t: Mismatch!", $time);
                $display("  Input A: %d, Input B: %d (Input cũ 5 nhịp trước)", a, b); 
                // Lưu ý: A, B hiển thị ở đây là A, B *mới* đang vào, không phải A, B tạo ra lỗi này
                // Muốn debug kỹ phải nhìn Waveform
                $display("  DUT Output : %h (%d)", p, p);
                $display("  Expected   : %h (%d)", exp_final, exp_final);
                error_count = error_count + 1;
            end
        end
    end

    // 6. STIMULUS (Kịch bản Test)
    initial begin
        // Khởi tạo
        rst = 1; a = 0; b = 0;
        #20; // Giữ reset 10 chu kỳ
        rst = 0;
        
        $display("==================================================");
        $display("   BẮT ĐẦU TEST BENCH CHO 5-STAGE PIPELINE");
        $display("==================================================");

        // --- TEST CASE 1: Cơ bản ---
        @(posedge clk); a = 2; b = 3;         // Exp = 6
        @(posedge clk); a = 10; b = 20;       // Exp = 200
        @(posedge clk); a = 100; b = 100;     // Exp = 10000

        // --- TEST CASE 2: Corner Cases (Số đặc biệt) ---
        @(posedge clk); a = 0; b = 12345;     // Nhân với 0
        @(posedge clk); a = 1; b = 99999;     // Nhân với 1
        @(posedge clk); a = 32'hFFFFFFFF; b = 1; // Số lớn nhất 32bit * 1
        @(posedge clk); a = 32'hFFFFFFFF; b = 32'hFFFFFFFF; // Max * Max (Test 64bit Output)

        // --- TEST CASE 3: Random Stress Test ---
        $display("Running 2000 Random Vectors...");
        repeat (2000) begin
            @(posedge clk);
            a = $urandom; 
            b = $urandom;
        end

        // Chờ kết quả cuối cùng chui ra khỏi ống
        repeat (10) @(posedge clk);

        $display("==================================================");
        if (error_count == 0) begin
            $display("   TEST PASSED! TUYỆT VỜI ÔNG MẶT TRỜI! :D");
            $display("   Mạch chạy đúng 5-Stage Pipeline.");
        end else begin
            $display("   TEST FAILED! Có %0d lỗi xảy ra.", error_count);
        end
        $display("==================================================");
        $finish;
    end

    // Tạo file sóng
    initial begin
        $dumpfile("tb_pipelined_mult.vcd");
        $dumpvars(0, tb_pipelined_mult);
    end

endmodule

verify/tb_pipelined_mult.vcd
$date
	Tue Jan  6 10:41:13 2026
$end
$version
	Icarus Verilog
$end
$timescale
	1ps
$end
$scope module tb_pipelined_mult $end
$var wire 64 ! p [63:0] $end
$var reg 32 " a [31:0] $end
$var reg 32 # b [31:0] $end
$var reg 1 $ clk $end
$var reg 64 % exp_1 [63:0] $end
$var reg 64 & exp_2 [63:0] $end
$var reg 64 ' exp_3 [63:0] $end
$var reg 64 ( exp_4 [63:0] $end
$var reg 64 ) exp_5 [63:0] $end
$var reg 64 * exp_final [63:0] $end
$var reg 1 + rst $end
$var integer 32 , error_count [31:0] $end
$scope module uut $end
$var wire 32 - a [31:0] $end
$var wire 32 . b [31:0] $end
$var wire 1 $ clk $end
$var wire 1 + rst $end
$var reg 16 / a_h [15:0] $end
$var reg 16 0 a_l [15:0] $end
$var reg 16 1 b_h [15:0] $end
$var reg 16 2 b_l [15:0] $end
$var reg 33 3 mid_sum [32:0] $end
$var reg 64 4 p [63:0] $end
$var reg 32 5 p_hh [31:0] $end
$var reg 32 6 p_hh_pipe [31:0] $end
$var reg 32 7 p_hl [31:0] $end
$var reg 32 8 p_lh [31:0] $end
$var reg 32 9 p_ll [31:0] $end
$var reg 32 : p_ll_pipe [31:0] $end
$var reg 64 ; term_high [63:0] $end
$var reg 64 < term_low [63:0] $end
$var reg 64 = term_mid [63:0] $end
$upscope $end
$upscope $end
$enddefinitions $end
$comment Show the parameter values. $end
$dumpall
$end
#0
$dumpvars
bx =
bx <
bx ;
bx :
bx 9
bx 8
bx 7
bx 6
bx 5
bx 4
bx 3
bx 2
bx 1
bx 0
bx /
b0 .
b0 -
b0 ,
1+
bx *
bx )
bx (
bx '
bx &
bx %
0$
b0 #
b0 "
bx !
$end
#1000
b0 *
b0 2
b0 1
b0 0
b0 /
b0 9
b0 8
b0 7
b0 5
b0 :
b0 6
b0 3
b0 <
b0 =
b0 ;
b0 !
b0 4
b0 )
b0 (
b0 '
b0 &
b0 %
1$
#2000
0$
#3000
1$
#4000
0$
#5000
1$
#6000
0$
#7000
1$
#8000
0$
#9000
1$
#10000
0$
#11000
1$
#12000
0$
#13000
1$
#14000
0$
#15000
1$
#16000
0$
#17000
1$
#18000
0$
#19000
1$
#20000
0$
0+
#21000
b11 2
b10 0
b110 %
b11 #
b11 .
b10 "
b10 -
1$
#22000
0$
#23000
b110 &
b110 9
b10100 #
b10100 .
b1010 "
b1010 -
1$
#24000
0$
#25000
b1100100 2
b1100100 0
b110 :
b110 '
b10011100010000 %
b1100100 #
b1100100 .
b1100100 "
b1100100 -
1$
#26000
0$
#27000
b110 (
b10011100010000 &
b110 <
b10011100010000 9
b11000000111001 #
b11000000111001 .
b0 "
b0 -
1$
#28000
0$
#29000
b110 *
b1000011010011111 2
b1 1
b1 0
b10011100010000 :
b110 !
b110 4
b110 )
b10011100010000 '
b11000011010011111 %
b11000011010011111 #
b11000011010011111 .
b1 "
b1 -
1$
#30000
0$
#31000
b10011100010000 (
b11000011010011111 &
b10011100010000 <
b1000011010011111 9
b1 8
b1 #
b1 .
b11111111111111111111111111111111 "
b11111111111111111111111111111111 -
1$
#32000
0$
#33000
b10011100010000 *
b1111111111111111 2
b1111111111111111 1
b1111111111111111 0
b1111111111111111 /
b1000011010011111 :
b1 3
b10011100010000 !
b10011100010000 4
b10011100010000 )
b11000011010011111 '
b1111111111111111111111111111111000000000000000000000000000000001 %
b11111111111111111111111111111111 #
b11111111111111111111111111111111 .
1$
#34000
0$
#35000
b11000011010011111 (
b1111111111111111111111111111111000000000000000000000000000000001 &
b1000011010011111 <
b10000000000000000 =
b11111111111111100000000000000001 9
b11111111111111100000000000000001 8
b11111111111111100000000000000001 7
b11111111111111100000000000000001 5
b1000000100010010101111010000001 #
b1000000100010010101111010000001 .
b10010010000101010011010100100100 "
b10010010000101010011010100100100 -
1$
#36000
0$
#37000
b11000011010011111 *
b101011001100011 2
b11000111110000 1
b1101011000001001 0
b10010000100 /
b11111111111111100000000000000001 :
b11111111111111100000000000000001 6
b111111111111111000000000000000010 3
b11000011010011111 !
b11000011010011111 4
b11000011010011111 )
b1111111111111111111111111111111000000000000000000000000000000001 '
b11100001101010110000011011000000101101011100101101111011 %
b110001111100000101011001100011 #
b110001111100000101011001100011 .
b100100001001101011000001001 "
b100100001001101011000001001 -
1$
#38000
0$
#39000
b1111111111111111111111111111111000000000000000000000000000000001 (
b11100001101010110000011011000000101101011100101101111011 &
b11111111111111100000000000000001 <
b1111111111111110000000000000000100000000000000000 =
b1111111111111110000000000000000100000000000000000000000000000000 ;
b1001000001110011100101101111011 9
b101001110000000110000101110000 8
b1100001100001011100001100 7
b111000010111111111000000 5
b11000110110111111001100110001101 #
b11000110110111111001100110001101 .
b10000110101110010111101100001101 "
b10000110101110010111101100001101 -
1$
#40000
0$
#41000
b1111111111111111111111111111111000000000000000000000000000000001 *
b101001000010010 2
b100100110111 1
b1000010001100101 0
b11001011000010 /
b1001000001110011100101101111011 :
b111000010111111111000000 6
b101011010001100111100001111100 3
b1111111111111111111111111111111000000000000000000000000000000001 !
b1111111111111111111111111111111000000000000000000000000000000001 4
b1111111111111111111111111111111000000000000000000000000000000001 )
b11100001101010110000011011000000101101011100101101111011 '
b111010011110011101011011111011110110010001010100100011010 %
b1001001101110101001000010010 #
b1001001101110101001000010010 .
b110010110000101000010001100101 "
b110010110000101000010001100101 -
1$
#42000
0$
#43000
b11100001101010110000011011000000101101011100101101111011 (
b111010011110011101011011111011110110010001010100100011010 &
b1001000001110011100101101111011 <
b1010110100011001111000011111000000000000000000 =
b11100001011111111100000000000000000000000000000000000000 ;
b101010011100011010100100011010 9
b100110000111111111010110011 8
b10000010001011011010110100100 7
b1110100111011100110101110 5
b10000110110101111100110100001101 #
b10000110110101111100110100001101 .
b10000000111100111110001100000001 "
b10000000111100111110001100000001 -
1$
#44000
0$
#45000
b11100001101010110000011011000000101101011100101101111011 *
b1100110100111101 2
b1001111010001101 1
b1111000101110110 0
b1011101100100011 /
b101010011100011010100100011010 :
b1110100111011100110101110 6
b10101000010011011010001010111 3
b11100001101010110000011011000000101101011100101101111011 !
b11100001101010110000011011000000101101011100101101111011 4
b11100001101010110000011011000000101101011100101101111011 )
b111010011110011101011011111011110110010001010100100011010 '
b111001111100111110101111101101100110001111010100000011100011110 %
b10011110100011011100110100111101 #
b10011110100011011100110100111101 .
b10111011001000111111000101110110 "
b10111011001000111111000101110110 -
1$
#46000
0$
#47000
b111010011110011101011011111011110110010001010100100011010 (
b111001111100111110101111101101100110001111010100000011100011110 &
b101010011100011010100100011010 <
b101010000100110110100010101110000000000000000 =
b111010011101110011010111000000000000000000000000000000000 ;
b11000001100101010000011100011110 9
b10010101100010111101000111111110 8
b10010110000001111001111001010111 7
b1110011111001101010110001000111 5
b11000110001011011111011110001100 #
b11000110001011011111011110001100 .
b11110110110101000101011111101101 "
b11110110110101000101011111101101 -
1$
#48000
0$
#49000
b111010011110011101011011111011110110010001010100100011010 *
b10010011000110 2
b110001100110111 1
b1110100111111001 0
b1111110011111101 /
b11000001100101010000011100011110 :
b1110011111001101010110001000111 6
b100101011100100110111000001010101 3
b111010011110011101011011111011110110010001010100100011010 !
b111010011110011101011011111011110110010001010100100011010 4
b111010011110011101011011111011110110010001010100100011010 )
b111001111100111110101111101101100110001111010100000011100011110 '
b110001000001100101100000101111111110000110010001111101010010110 %
b1100011001101110010010011000110 #
b1100011001101110010010011000110 .
b11111100111111011110100111111001 "
b11111100111111011110100111111001 -
1$
#50000
0$
#51000
b111001111100111110101111101101100110001111010100000011100011110 (
b110001000001100101100000101111111110000110010001111101010010110 &
b11000001100101010000011100011110 <
b1001010111001001101110000010101010000000000000000 =
b111001111100110101011000100011100000000000000000000000000000000 ;
b100001100110111111101010010110 9
b1011010101011011000111101111111 8
b100100010101110011111110101110 7
b1100010000011000011000101011011 5
b1010101000100111101001010101010 #
b1010101000100111101001010101010 .
b1100010111101111000010011000101 "
b1100010111101111000010011000101 -
1$
#52000
0$
#53000
b111001111100111110101111101101100110001111010100000011100011110 *
b111001001110111 2
b11101111010010 1
b1111011111100101 0
b1111001010101111 /
b100001100110111111101010010110 :
b1100010000011000011000101011011 6
b1111111000001001100111100101101 3
b111001111100111110101111101101100110001111010100000011100011110 !
b111001111100111110101111101101100110001111010100000011100011110 4
b111001111100111110101111101101100110001111010100000011100011110 )
b110001000001100101100000101111111110000110010001111101010010110 '
b11100010110110000011101111111001001101000010100011010101110011 %
b111011110100100111001001110111 #
b111011110100100111001001110111 .
b11110010101011111111011111100101 "
b11110010101011111111011111100101 -
1$
#54000
0$
#55000
b110001000001100101100000101111111110000110010001111101010010110 (
b11100010110110000011101111111001001101000010100011010101110011 &
b100001100110111111101010010110 <
b11111110000010011001111001011010000000000000000 =
b110001000001100001100010101101100000000000000000000000000000000 ;
b1101110110101110011010101110011 9
b111001111011010010000011011010 8
b1101100100000101011110101011001 7
b111000101101010110100010001110 5
b11000111111011001101101110001111 #
b11000111111011001101101110001111 .
b1001001100101101011000010010 "
b1001001100101101011000010010 -
1$
#56000
0$
#57000
b110001000001100101100000101111111110000110010001111101010010110 *
b1001011011001110 2
b110011101110110 1
b110100111110010 0
b1111100100110000 /
b1101110110101110011010101110011 :
b111000101101010110100010001110 6
b10100110011011111101111000110011 3
b110001000001100101100000101111111110000110010001111101010010110 !
b110001000001100101100000101111111110000110010001111101010010110 4
b110001000001100101100000101111111110000110010001111101010010110 )
b11100010110110000011101111111001001101000010100011010101110011 '
b110010010110101111010011011110000010110100101010000110010111100 %
b1100111011101101001011011001110 #
b1100111011101101001011011001110 .
b11111001001100000110100111110010 "
b11111001001100000110100111110010 -
1$
#58000
0$
#59000
b11100010110110000011101111111001001101000010100011010101110011 (
b110010010110101111010011011110000010110100101010000110010111100 &
b1101110110101110011010101110011 <
b101001100110111111011110001100110000000000000000 =
b11100010110101011010001000111000000000000000000000000000000000 ;
b111110011010010000110010111100 9
b101010110100010011001110001100 8
b10010010110010101010010010100000 7
b1100100101101010010110000100000 5
b1100010110010100100111011000101 #
b1100010110010100100111011000101 .
b1110100000000000111101011101000 "
b1110100000000000111101011101000 -
1$
#60000
0$
#61000
b11100010110110000011101111111001001101000010100011010101110011 *
b10100010111101 2
b101111010001110 1
b100100101011100 0
b1010111001011000 /
b111110011010010000110010111100 :
b1100100101101010010110000100000 6
b10111101100110111101100000101100 3
b11100010110110000011101111111001001101000010100011010101110011 !
b11100010110110000011101111111001001101000010100011010101110011 4
b11100010110110000011101111111001001101000010100011010101110011 )
b110010010110101111010011011110000010110100101010000110010111100 '
b100000001100101001110111010011011111011101011001000100011101100 %
b1011110100011100010100010111101 #
b1011110100011100010100010111101 .
b10101110010110000100100101011100 "
b10101110010110000100100101011100 -
1$
#62000
0$
#63000
b110010010110101111010011011110000010110100101010000110010111100 (
b100000001100101001110111010011011111011101011001000100011101100 &
b111110011010010000110010111100 <
b101111011001101111011000001011000000000000000000 =
b110010010110101001011000010000000000000000000000000000000000000 ;
b1011101011001000100011101100 9
b11011000110000111100100001000 8
b11011101111100111011011111000 7
b1000000011001010000010011010000 5
b110010101001110010011001100101 #
b110010101001110010011001100101 .
b10110101010110101100000101101 "
b10110101010110101100000101101 -
1$
#64000
0$
#65000
b110010010110101111010011011110000010110100101010000110010111100 *
b1000011100001010 2
b1000010101110011 1
b110001001100011 0
b11000111101111 /
b1011101011001000100011101100 :
b1000000011001010000010011010000 6
b110110110101101111000000000000 3
b110010010110101111010011011110000010110100101010000110010111100 !
b110010010110101111010011011110000010110100101010000110010111100 4
b110010010110101111010011011110000010110100101010000110010111100 )
b100000001100101001110111010011011111011101011001000100011101100 '
b1101000000111111001101111110111010001101101010000110011011110 %
b10000101011100111000011100001010 #
b10000101011100111000011100001010 .
b110001111011110110001001100011 "
b110001111011110110001001100011 -
1$
#66000
0$
#67000
b100000001100101001110111010011011111011101011001000100011101100 (
b1101000000111111001101111110111010001101101010000110011011110 &
b1011101011001000100011101100 <
b1101101101011011110000000000000000000000000000 =
b100000001100101000001001101000000000000000000000000000000000000 ;
b110011111001100000110011011110 9
b110011010010011010000101111001 8
b11010010101101111110001010110 7
b11010000001111001100101011101 5
b10010000011001000010000100100000 #
b10010000011001000010000100100000 .
b1000000001110110010001010000000 "
b1000000001110110010001010000000 -
1$
#68000
0$
#69000
b100000001100101001110111010011011111011101011001000100011101100 *
b1100110010011101 2
b100111011001100 1
b100010110101010 0
b1101010101111000 /
b110011111001100000110011011110 :
b11010000001111001100101011101 6
b1001101101000001001110111001111 3
b100000001100101001110111010011011111011101011001000100011101100 !
b100000001100101001110111010011011111011101011001000100011101100 4
b100000001100101001110111010011011111011101011001000100011101100 )
b1101000000111111001101111110111010001101101010000110011011110 '
b100000110110101011010111011000000010001101111100011000101000010 %
b1001110110011001100110010011101 #
b1001110110011001100110010011101 .
b11010101011110000100010110101010 "
b11010101011110000100010110101010 -
1$
#70000
0$
#71000
b1101000000111111001101111110111010001101101010000110011011110 (
b100000110110101011010111011000000010001101111100011000101000010 &
b110011111001100000110011011110 <
b10011011010000010011101110011110000000000000000 =
b1101000000111100110010101110100000000000000000000000000000000 ;
b110111101011100011000101000010 9
b10101011100010100111101111000 8
b10101010100111101000101010011000 7
b1000001101101001010101110100000 5
b1001100000111011100000010011 #
b1001100000111011100000010011 .
b1001011001000000011111010010110 "
b1001011001000000011111010010110 -
1$
#72000
0$
#73000
b1101000000111111001101111110111010001101101010000110011011110 *
b1101011001010011 2
b10100110100111 1
b11100000001101 0
b11010111100 /
b110111101011100011000101000010 :
b1000001101101001010101110100000 6
b11000000000011111101101000010000 3
b1101000000111111001101111110111010001101101010000110011011110 !
b1101000000111111001101111110111010001101101010000110011011110 4
b1101000000111111001101111110111010001101101010000110011011110 )
b100000110110101011010111011000000010001101111100011000101000010 '
b100011000100011110110011000101011010111000000101000110111 %
b101001101001111101011001010011 #
b101001101001111101011001010011 .
b110101111000011100000001101 "
b110101111000011100000001101 -
1$
#74000
0$
#75000
b100000110110101011010111011000000010001101111100011000101000010 (
b100011000100011110110011000101011010111000000101000110111 &
b110111101011100011000101000010 <
b110000000000111111011010000100000000000000000000 =
b100000110110100101010111010000000000000000000000000000000000000 ;
b101110111011010000101000110111 9
b1001000111101010010101111011 8
b101101000110101011011110100 7
b1000110001000000010100100 5
b1101010101001100010101011010101 #
b1101010101001100010101011010101 .
b10110101100111111101110101101011 "
b10110101100111111101110101101011 -
1$
#76000
0$
#77000
b100000110110101011010111011000000010001101111100011000101000010 *
b11111010101110 2
b101011101010110 1
b100101000000010 0
b100010111 /
b101110111011010000101000110111 :
b1000110001000000010100100 6
b1110110000011111110001101111 3
b100000110110101011010111011000000010001101111100011000101000010 !
b100000110110101011010111011000000010001101111100011000101000010 4
b100000110110101011010111011000000010001101111100011000101000010 )
b100011000100011110110011000101011010111000000101000110111 '
b1011111010010000011110111101100011011001100100101011100 %
b1010111010101100011111010101110 #
b1010111010101100011111010101110 .
b1000101110100101000000010 "
b1000101110100101000000010 -
1$
#78000
0$
#79000
b100011000100011110110011000101011010111000000101000110111 (
b1011111010010000011110111101100011011001100100101011100 &
b101110111011010000101000110111 <
b11101100000111111100011011110000000000000000 =
b100011000100000001010010000000000000000000000000000000000 ;
b10010000111101100100101011100 9
b11001001111111000101010101100 8
b10001000100111110100010 7
b10111110010111010111010 5
b1100111110001010111001011001111 #
b1100111110001010111001011001111 .
b10001110111111111110100100011101 "
b10001110111111111110100100011101 -
1$
#80000
0$
#81000
b100011000100011110110011000101011010111000000101000110111 *
b110010100001010 2
b1000010100001001 1
b100100100100011 0
b1001000110000100 /
b10010000111101100100101011100 :
b10111110010111010111010 6
b11001100000111101101001001110 3
b100011000100011110110011000101011010111000000101000110111 !
b100011000100011110110011000101011010111000000101000110111 4
b100011000100011110110011000101011010111000000101000110111 )
b1011111010010000011110111101100011011001100100101011100 '
b100101110011111000100010001010010100001010000001010101001011110 %
b10000101000010010110010100001010 #
b10000101000010010110010100001010 .
b10010001100001000100100100100011 "
b10010001100001000100100100100011 -
1$
#82000
0$
#83000
b1011111010010000011110111101100011011001100100101011100 (
b100101110011111000100010001010010100001010000001010101001011110 &
b10010000111101100100101011100 <
b110011000001111011010010011100000000000000000 =
b1011111001011101011101000000000000000000000000000000000 ;
b11100110111011010101001011110 9
b100110000000011100000100111011 8
b111001011011101100001100101000 7
b1001011100111101011000110100100 5
b11110001100010100110000111100 #
b11110001100010100110000111100 .
b1100101011100110000101011001010 "
b1100101011100110000101011001010 -
1$
#84000
0$
#85000
b1011111010010000011110111101100011011001100100101011100 *
b110000110001010 2
b1100010100101110 1
b1011110111110010 0
b1111100101101000 /
b11100110111011010101001011110 :
b1001011100111101011000110100100 6
b1011111011100001000010001100011 3
b1011111010010000011110111101100011011001100100101011100 !
b1011111010010000011110111101100011011001100100101011100 4
b1011111010010000011110111101100011011001100100101011100 )
b100101110011111000100010001010010100001010000001010101001011110 '
b1100000000011010110010100000010001111101111010110001011001110100 %
b11000101001011100110000110001010 #
b11000101001011100110000110001010 .
b11111001011010001011110111110010 "
b11111001011010001011110111110010 -
1$
#86000
0$
#87000
b100101110011111000100010001010010100001010000001010101001011110 (
b1100000000011010110010100000010001111101111010110001011001110100 &
b11100110111011010101001011110 <
b10111110111000010000100011000110000000000000000 =
b100101110011110101100011010010000000000000000000000000000000000 ;
b1001000010111110001011001110100 9
b10010010010011010101101101111100 8
b1011111000001101101101000010000 7
b11000000000110011101100010110000 5
b1101100010010110011010011011000 #
b1101100010010110011010011011000 .
b10100000110001001011001101000001 "
b10100000110001001011001101000001 -
1$
#88000
0$
#89000
b100101110011111000100010001010010100001010000001010101001011110 *
b1001010001001 2
b100010010001010 1
b1111001101111000 0
b1011110000100000 /
b1001000010111110001011001110100 :
b11000000000110011101100010110000 6
b11110001010101000011010110001100 3
b100101110011111000100010001010010100001010000001010101001011110 !
b100101110011111000100010001010010100001010000001010101001011110 4
b100101110011111000100010001010010100001010000001010101001011110 )
b1100000000011010110010100000010001111101111010110001011001110100 '
b11001001011110001110000000111000011101011100001011101100111000 %
b1000100100010100001001010001001 #
b1000100100010100001001010001001 .
b10111100001000001111001101111000 "
b10111100001000001111001101111000 -
1$
#90000
0$
#91000
b1100000000011010110010100000010001111101111010110001011001110100 (
b11001001011110001110000000111000011101011100001011101100111000 &
b1001000010111110001011001110100 <
b111100010101010000110101100011000000000000000000 =
b1100000000011001110110001011000000000000000000000000000000000000 ;
b10001101000001011101100111000 9
b1000001001011110001111010110000 8
b1101100111101110110100100000 7
b110010010111011110100101000000 5
b11011011000000100110010110110110 #
b11011011000000100110010110110110 .
b11110101110001010000110111101011 "
b11110101110001010000110111101011 -
1$
#92000
0$
#93000
b1100000000011010110010100000010001111101111010110001011001110100 *
b1001110101110 2
b1101011100010101 1
b1111100111000110 0
b1110001101001011 /
b10001101000001011101100111000 :
b110010010111011110100101000000 6
b1001110110011100000101111010000 3
b1100000000011010110010100000010001111101111010110001011001110100 !
b1100000000011010110010100000010001111101111010110001011001110100 4
b1100000000011010110010100000010001111101111010110001011001110100 )
b11001001011110001110000000111000011101011100001011101100111000 '
b1011111011110111100001010111100111101000011010110111011010010100 %
b11010111000101010001001110101110 #
b11010111000101010001001110101110 .
b11100011010010111111100111000110 "
b11100011010010111111100111000110 -
1$
#94000
0$
#95000
b11001001011110001110000000111000011101011100001011101100111000 (
b1011111011110111100001010111100111101000011010110111011010010100 &
b10001101000001011101100111000 <
b10011101100111000001011110100000000000000000000 =
b11001001011101111010010100000000000000000000000000000000000000 ;
b10011001100110111011010010100 9
b11010001110110011100011100111110 8
b10001011110010000110111111010 7
b10111110111101101010001000100111 5
b10010101000011111101110100101010 #
b10010101000011111101110100101010 .
b1011110011101010000001010111100 "
b1011110011101010000001010111100 -
1$
#96000
0$
#97000
b11001001011110001110000000111000011101011100001011101100111000 *
b1011111001110001 2
b11100010010111 1
b1001101000001011 0
b10111010111 /
b10011001100110111011010010100 :
b10111110111101101010001000100111 6
b11100011010100101101010100111000 3
b11001001011110001110000000111000011101011100001011101100111000 !
b11001001011110001110000000111000011101011100001011101100111000 4
b11001001011110001110000000111000011101011100001011101100111000 )
b1011111011110111100001010111100111101000011010110111011010010100 '
b101001010101000000011011011011100111111000010100011011011 %
b111000100101111011111001110001 #
b111000100101111011111001110001 .
b101110101111001101000001011 "
b101110101111001101000001011 -
1$
#98000
0$
#99000
b1011111011110111100001010111100111101000011010110111011010010100 (
b101001010101000000011011011011100111111000010100011011011 &
b10011001100110111011010010100 <
b111000110101001011010101001110000000000000000000 =
b1011111011110110101000100010011100000000000000000000000000000000 ;
b1110010100110000010100011011011 9
b100010000011010100010001111101 8
b100010110000010010111100111 7
b1010010100111100111010001 5
b10100111111100100101010101001111 #
b10100111111100100101010101001111 .
b11000010111100100100000110000101 "
b11000010111100100100000110000101 -
1$
#100000
0$
#101000
b1011111011110111100001010111100111101000011010110111011010010100 *
b11001100111010 2
b1001110100000110 1
b110000000111011 0
b1110111001100 /
b1110010100110000010100011011011 :
b1010010100111100111010001 6
b100110011001010110101001100100 3
b1011111011110111100001010111100111101000011010110111011010010100 !
b1011111011110111100001010111100111101000011010110111011010010100 4
b1011111011110111100001010111100111101000011010110111011010010100 )
b101001010101000000011011011011100111111000010100011011011 '
b1001001000111000011111100010011100111110110111000111001011110 %
b10011101000001100011001100111010 #
b10011101000001100011001100111010 .
b11101110011000110000000111011 "
b11101110011000110000000111011 -
1$
#102000
0$
#103000
b101001010101000000011011011011100111111000010100011011011 (
b1001001000111000011111100010011100111110110111000111001011110 &
b1110010100110000010100011011011 <
b1001100110010101101010011001000000000000000000 =
b101001010011110011101000100000000000000000000000000000000 ;
b10011010000011000111001011110 9
b111011000001100111000001100010 8
b101111101100110010000111000 7
b10010010001101100111011001000 5
b10001010101010100100101100010101 #
b10001010101010100100101100010101 .
b111111001000110011001001111110 "
b111111001000110011001001111110 -
1$
#104000
0$
#105000
b101001010101000000011011011011100111111000010100011011011 *
b100101111011001 2
b1110110010011100 1
b1001101111110001 0
b1111100011011001 /
b10011010000011000111001011110 :
b10010010001101100111011001000 6
b1000000111111001101010010011010 3
b101001010101000000011011011011100111111000010100011011011 !
b101001010101000000011011011011100111111000010100011011011 4
b101001010101000000011011011011100111111000010100011011011 )
b1001001000111000011111100010011100111110110111000111001011110 '
b1110011000000000100010100001011111100100000000001100101001001001 %
b11101100100111000100101111011001 #
b11101100100111000100101111011001 .
b11111000110110011001101111110001 "
b11111000110110011001101111110001 -
1$
#106000
0$
#107000
b1001001000111000011111100010011100111110110111000111001011110 (
b1110011000000000100010100001011111100100000000001100101001001001 &
b10011010000011000111001011110 <
b10000001111110011010100100110100000000000000000 =
b1001001000110110011101100100000000000000000000000000000000000 ;
b101110001100111100101001001001 9
b10010000001000010011001011011100 8
b1001001101110101000001011110001 7
b11100101111111111011000000111100 5
b10100110001101011111101101001100 #
b10100110001101011111101101001100 .
b10110001001000110000011101100010 "
b10110001001000110000011101100010 -
1$
#108000
0$
#109000
b1001001000111000011111100010011100111110110111000111001011110 *
b1010000110001111 2
b1100011110111001 1
b101010110011111 0
b1100111110100001 /
b101110001100111100101001001001 :
b11100101111111111011000000111100 6
b11011001110110111011010111001101 3
b1001001000111000011111100010011100111110110111000111001011110 !
b1001001000111000011111100010011100111110110111000111001011110 4
b1001001000111000011111100010011100111110110111000111001011110 )
b1110011000000000100010100001011111100100000000001100101001001001 '
b1010000111111100111110000010110111101010110111101101001011010001 %
b11000111101110011010000110001111 #
b11000111101110011010000110001111 .
b11001111101000010101010110011111 "
b11001111101000010101010110011111 -
1$
#110000
0$
